nox_tools/__init__.py
nox_tools/py.typed
nox_tools/sessions.py
nox_tools-0.2.0.dist-info/LICENSE
nox_tools-0.2.0.dist-info/WHEEL
nox_tools-0.2.0.dist-info/METADATA
nox_tools-0.2.0.dist-info/RECORD
