Metadata-Version: 2.1
Name: nox_tools
Version: 0.2.0
Summary: Predefined sessions for nox
Author-email: Ali Ghahraei Figueroa <aligf94@gmail.com>
Classifier: Programming Language :: Python :: 3
Classifier: License :: OSI Approved :: MIT License
Classifier: Operating System :: POSIX :: Linux
Classifier: Operating System :: MacOS
Classifier: Operating System :: Unix
Requires-Dist: nox
Project-URL: Home, https://github.com/AliGhahraei/nox-tools
